rereferencer/__init__.py
rereferencer/__main__.py
rereferencer/cli.py
rereferencer/core.py
rereferencer-0.1.4.dist-info/licenses/LICENSE
rereferencer-0.1.4.dist-info/METADATA
rereferencer-0.1.4.dist-info/WHEEL
rereferencer-0.1.4.dist-info/entry_points.txt
rereferencer-0.1.4.dist-info/top_level.txt
rereferencer-0.1.4.dist-info/RECORD
