Metadata-Version: 2.4
Name: rereferencer
Version: 0.1.4
Summary: A tool to extract amplified regions from reference sequences using primer pairs
Home-page: https://github.com/SemiQuant/rereferencer
Author: SemiQuant
Author-email: SemiQuant <JasonLimberis@ucsf.edu>
License-Expression: MIT
Project-URL: Homepage, https://github.com/SemiQuant/rereferencer
Project-URL: Repository, https://github.com/SemiQuant/rereferencer.git
Classifier: Programming Language :: Python :: 3
Classifier: Operating System :: OS Independent
Requires-Python: >=3.7
License-File: LICENSE
Requires-Dist: click>=8.0.0
Requires-Dist: biopython>=1.81
Requires-Dist: pandas>=2.0.0
Requires-Dist: rich>=13.0.0
Dynamic: author
Dynamic: home-page
Dynamic: license-file
Dynamic: requires-python
